decohints/__init__.py
decohints/main.py
decohints/py.typed
decohints-1.0.9.dist-info/LICENSE
decohints-1.0.9.dist-info/METADATA
decohints-1.0.9.dist-info/WHEEL
decohints-1.0.9.dist-info/top_level.txt
decohints-1.0.9.dist-info/RECORD
