Metadata-Version: 2.1
Name: decohints
Version: 1.0.9
Summary: A decorator for decorators that allows you to see the parameters of a decorated function when using it in PyCharm.
Home-page: https://github.com/gri-gus/decohints
Author: Grigoriy Gusev
Author-email: thegrigus@gmail.com
License: Apache Software License
Keywords: python,decorator,deco,decohints,hints,decor,decohint,python-decorator,helper,util
Platform: UNKNOWN
Classifier: Programming Language :: Python :: 3.7
Classifier: License :: OSI Approved :: Apache Software License
Classifier: Operating System :: OS Independent
Requires-Python: >=3.5
License-File: LICENSE
